animefan/__init__.py
animefan/main.py
animefan/ascii-images/img100-ascii-art.txt
animefan/ascii-images/img12-ascii-art.txt
animefan/ascii-images/img14-ascii-art.txt
animefan/ascii-images/img15-ascii-art.txt
animefan/ascii-images/img16-ascii-art.txt
animefan/ascii-images/img17-ascii-art.txt
animefan/ascii-images/img18-ascii-art.txt
animefan/ascii-images/img19-ascii-art.txt
animefan/ascii-images/img2-ascii-art.txt
animefan/ascii-images/img20-ascii-art.txt
animefan/ascii-images/img22-ascii-art.txt
animefan/ascii-images/img23-ascii-art.txt
animefan/ascii-images/img25-ascii-art.txt
animefan/ascii-images/img26-ascii-art.txt
animefan/ascii-images/img27-ascii-art.txt
animefan/ascii-images/img29-ascii-art.txt
animefan/ascii-images/img3-ascii-art.txt
animefan/ascii-images/img30-ascii-art.txt
animefan/ascii-images/img33-ascii-art.txt
animefan/ascii-images/img34-ascii-art.txt
animefan/ascii-images/img36-ascii-art.txt
animefan/ascii-images/img37-ascii-art.txt
animefan/ascii-images/img38-ascii-art.txt
animefan/ascii-images/img39-ascii-art.txt
animefan/ascii-images/img4-ascii-art.txt
animefan/ascii-images/img40-ascii-art.txt
animefan/ascii-images/img41-ascii-art.txt
animefan/ascii-images/img42-ascii-art.txt
animefan/ascii-images/img45-ascii-art.txt
animefan/ascii-images/img47-ascii-art.txt
animefan/ascii-images/img48-ascii-art.txt
animefan/ascii-images/img49-ascii-art.txt
animefan/ascii-images/img5-ascii-art.txt
animefan/ascii-images/img50-ascii-art.txt
animefan/ascii-images/img51-ascii-art.txt
animefan/ascii-images/img52-ascii-art.txt
animefan/ascii-images/img53-ascii-art.txt
animefan/ascii-images/img54-ascii-art.txt
animefan/ascii-images/img55-ascii-art.txt
animefan/ascii-images/img56-ascii-art.txt
animefan/ascii-images/img57-ascii-art.txt
animefan/ascii-images/img58-ascii-art.txt
animefan/ascii-images/img59-ascii-art.txt
animefan/ascii-images/img62-ascii-art.txt
animefan/ascii-images/img63-ascii-art.txt
animefan/ascii-images/img64-ascii-art.txt
animefan-1.1.4.dist-info/LICENSE
animefan-1.1.4.dist-info/METADATA
animefan-1.1.4.dist-info/WHEEL
animefan-1.1.4.dist-info/entry_points.txt
animefan-1.1.4.dist-info/top_level.txt
animefan-1.1.4.dist-info/RECORD
